pytest_when-2.3.0.dist-info/METADATA
pytest_when-2.3.0.dist-info/WHEEL
pytest_when-2.3.0.dist-info/entry_points.txt
pytest_when-2.3.0.dist-info/licenses/LICENSE
pytest_when/__init__.py
pytest_when/constant.py
pytest_when/interface.py
pytest_when/plugin.py
pytest_when/py.typed
pytest_when/when.py
pytest_when-2.3.0.dist-info/RECORD
