Metadata-Version: 2.1
Name: pytest-when
Version: 2.3.0
Summary: Utility which makes mocking more readable and controllable
Author-Email: zhukovgreen <iam+pytest-when@zhukovgreen.pro>
Project-URL: repository, https://github.com/zhukovgreen/pytest-when
Requires-Python: >=3.10
Requires-Dist: pytest>=7.3.1
Requires-Dist: pytest-mock>=3.14.0
Requires-Dist: typing-extensions>=4.5.0
Requires-Dist: friendly-sequences>=1.10
